mi_libreria_test/__init__.py
mi_libreria_test-0.1.0.dist-info/METADATA
mi_libreria_test-0.1.0.dist-info/WHEEL
mi_libreria_test-0.1.0.dist-info/RECORD
